{
  "annotations": {
    "list": [
      {
        "builtIn": 1,
        "datasource": {
          "type": "grafana",
          "uid": "-- Grafana --"
        },
        "enable": true,
        "hide": true,
        "iconColor": "rgba(0, 211, 255, 1)",
        "name": "Annotations & Alerts",
        "target": {
          "limit": 100,
          "matchAny": false,
          "tags": [],
          "type": "dashboard"
        },
        "type": "dashboard"
      }
    ]
  },
  "editable": true,
  "fiscalYearStartMonth": 0,
  "graphTooltip": 0,
  "id": 72,
  "links": [],
  "liveNow": false,
  "panels": [
    {
      "datasource": {
        "type": "prometheus",
        "uid": "ci-logs-prod-aks-geneva-integration"
      },
      "fieldConfig": {
        "defaults": {
          "color": {
            "mode": "palette-classic"
          },
          "custom": {
            "axisCenteredZero": false,
            "axisColorMode": "text",
            "axisLabel": "",
            "axisPlacement": "auto",
            "barAlignment": 0,
            "drawStyle": "line",
            "fillOpacity": 0,
            "gradientMode": "none",
            "hideFrom": {
              "legend": false,
              "tooltip": false,
              "viz": false
            },
            "lineInterpolation": "linear",
            "lineWidth": 1,
            "pointSize": 5,
            "scaleDistribution": {
              "type": "linear"
            },
            "showPoints": "auto",
            "spanNulls": false,
            "stacking": {
              "group": "A",
              "mode": "none"
            },
            "thresholdsStyle": {
              "mode": "off"
            }
          },
          "mappings": [],
          "thresholds": {
            "mode": "absolute",
            "steps": [
              {
                "color": "green",
                "value": null
              },
              {
                "color": "red",
                "value": 80
              }
            ]
          }
        },
        "overrides": []
      },
      "gridPos": {
        "h": 8,
        "w": 8,
        "x": 0,
        "y": 0
      },
      "id": 6,
      "options": {
        "legend": {
          "calcs": [],
          "displayMode": "list",
          "placement": "bottom",
          "showLegend": true
        },
        "tooltip": {
          "mode": "single",
          "sort": "none"
        }
      },
      "targets": [
        {
          "datasource": {
            "type": "prometheus",
            "uid": "ci-logs-prod-aks-geneva-integration"
          },
          "editorMode": "code",
          "expr": "sum by () (rate(fluentbit_input_records_total{name=~\"$namespace-*\"}[5m]))",
          "legendFormat": "All",
          "range": true,
          "refId": "A"
        }
      ],
      "title": "Fluent-bit input records/s by All Nodes",
      "type": "timeseries"
    },
    {
      "datasource": {
        "type": "prometheus",
        "uid": "ci-logs-prod-aks-geneva-integration"
      },
      "fieldConfig": {
        "defaults": {
          "color": {
            "mode": "palette-classic"
          },
          "custom": {
            "axisCenteredZero": false,
            "axisColorMode": "text",
            "axisLabel": "",
            "axisPlacement": "auto",
            "barAlignment": 0,
            "drawStyle": "line",
            "fillOpacity": 0,
            "gradientMode": "none",
            "hideFrom": {
              "legend": false,
              "tooltip": false,
              "viz": false
            },
            "lineInterpolation": "linear",
            "lineWidth": 1,
            "pointSize": 5,
            "scaleDistribution": {
              "type": "linear"
            },
            "showPoints": "auto",
            "spanNulls": false,
            "stacking": {
              "group": "A",
              "mode": "none"
            },
            "thresholdsStyle": {
              "mode": "off"
            }
          },
          "mappings": [],
          "thresholds": {
            "mode": "absolute",
            "steps": [
              {
                "color": "green",
                "value": null
              },
              {
                "color": "red",
                "value": 80
              }
            ]
          }
        },
        "overrides": []
      },
      "gridPos": {
        "h": 7,
        "w": 8,
        "x": 8,
        "y": 0
      },
      "id": 8,
      "options": {
        "legend": {
          "calcs": [],
          "displayMode": "list",
          "placement": "bottom",
          "showLegend": true
        },
        "tooltip": {
          "mode": "single",
          "sort": "none"
        }
      },
      "targets": [
        {
          "datasource": {
            "type": "prometheus",
            "uid": "ci-logs-prod-aks-geneva-integration"
          },
          "editorMode": "code",
          "expr": "sum by () (rate(fluentbit_output_proc_records_total{name=~\"$namespace-*\"}[5m]))",
          "legendFormat": "All",
          "range": true,
          "refId": "A"
        }
      ],
      "title": "Fluent-bit output process records/s by All Nodes",
      "type": "timeseries"
    },
    {
      "datasource": {
        "type": "prometheus",
        "uid": "ci-logs-prod-aks-geneva-integration"
      },
      "fieldConfig": {
        "defaults": {
          "color": {
            "mode": "palette-classic"
          },
          "custom": {
            "axisCenteredZero": false,
            "axisColorMode": "text",
            "axisLabel": "",
            "axisPlacement": "auto",
            "barAlignment": 0,
            "drawStyle": "line",
            "fillOpacity": 0,
            "gradientMode": "none",
            "hideFrom": {
              "legend": false,
              "tooltip": false,
              "viz": false
            },
            "lineInterpolation": "linear",
            "lineWidth": 1,
            "pointSize": 5,
            "scaleDistribution": {
              "type": "linear"
            },
            "showPoints": "auto",
            "spanNulls": false,
            "stacking": {
              "group": "A",
              "mode": "none"
            },
            "thresholdsStyle": {
              "mode": "off"
            }
          },
          "mappings": [],
          "thresholds": {
            "mode": "absolute",
            "steps": [
              {
                "color": "green",
                "value": null
              },
              {
                "color": "red",
                "value": 80
              }
            ]
          }
        },
        "overrides": []
      },
      "gridPos": {
        "h": 9,
        "w": 8,
        "x": 8,
        "y": 7
      },
      "id": 4,
      "options": {
        "legend": {
          "calcs": [],
          "displayMode": "list",
          "placement": "bottom",
          "showLegend": true
        },
        "tooltip": {
          "mode": "single",
          "sort": "none"
        }
      },
      "targets": [
        {
          "datasource": {
            "type": "prometheus",
            "uid": "ci-logs-prod-aks-geneva-integration"
          },
          "editorMode": "code",
          "expr": "sum by (node) (rate(fluentbit_output_proc_records_total{name=~\"$namespace-*\"}[5m]))",
          "legendFormat": "{{node}}",
          "range": true,
          "refId": "A"
        }
      ],
      "title": "Fluent-bit output process records/s by Node",
      "type": "timeseries"
    },
    {
      "datasource": {
        "type": "prometheus",
        "uid": "ci-logs-prod-aks-geneva-integration"
      },
      "description": "",
      "fieldConfig": {
        "defaults": {
          "color": {
            "mode": "palette-classic"
          },
          "custom": {
            "axisCenteredZero": false,
            "axisColorMode": "text",
            "axisLabel": "",
            "axisPlacement": "auto",
            "barAlignment": 0,
            "drawStyle": "line",
            "fillOpacity": 0,
            "gradientMode": "none",
            "hideFrom": {
              "legend": false,
              "tooltip": false,
              "viz": false
            },
            "lineInterpolation": "linear",
            "lineWidth": 1,
            "pointSize": 5,
            "scaleDistribution": {
              "type": "linear"
            },
            "showPoints": "auto",
            "spanNulls": false,
            "stacking": {
              "group": "A",
              "mode": "none"
            },
            "thresholdsStyle": {
              "mode": "off"
            }
          },
          "mappings": [],
          "thresholds": {
            "mode": "absolute",
            "steps": [
              {
                "color": "green",
                "value": null
              },
              {
                "color": "red",
                "value": 80
              }
            ]
          }
        },
        "overrides": []
      },
      "gridPos": {
        "h": 8,
        "w": 8,
        "x": 0,
        "y": 8
      },
      "id": 2,
      "options": {
        "legend": {
          "calcs": [],
          "displayMode": "list",
          "placement": "bottom",
          "showLegend": true
        },
        "tooltip": {
          "mode": "single",
          "sort": "none"
        }
      },
      "targets": [
        {
          "datasource": {
            "type": "prometheus",
            "uid": "ci-logs-prod-aks-geneva-integration"
          },
          "editorMode": "code",
          "expr": "sum by (node) (rate(fluentbit_input_records_total{name=~\"$namespace-*\"}[5m]))",
          "legendFormat": "{{node}}",
          "range": true,
          "refId": "A"
        }
      ],
      "title": "Fluent-bit input records/s by Node",
      "type": "timeseries"
    },
    {
      "datasource": {
        "type": "prometheus",
        "uid": "ci-logs-prod-aks-geneva-integration"
      },
      "fieldConfig": {
        "defaults": {
          "color": {
            "mode": "palette-classic"
          },
          "custom": {
            "axisCenteredZero": false,
            "axisColorMode": "text",
            "axisLabel": "",
            "axisPlacement": "auto",
            "barAlignment": 0,
            "drawStyle": "line",
            "fillOpacity": 0,
            "gradientMode": "none",
            "hideFrom": {
              "legend": false,
              "tooltip": false,
              "viz": false
            },
            "lineInterpolation": "linear",
            "lineWidth": 1,
            "pointSize": 5,
            "scaleDistribution": {
              "type": "linear"
            },
            "showPoints": "auto",
            "spanNulls": false,
            "stacking": {
              "group": "A",
              "mode": "none"
            },
            "thresholdsStyle": {
              "mode": "off"
            }
          },
          "mappings": [],
          "thresholds": {
            "mode": "absolute",
            "steps": [
              {
                "color": "green",
                "value": null
              },
              {
                "color": "red",
                "value": 80
              }
            ]
          }
        },
        "overrides": []
      },
      "gridPos": {
        "h": 8,
        "w": 8,
        "x": 0,
        "y": 16
      },
      "id": 10,
      "options": {
        "legend": {
          "calcs": [],
          "displayMode": "list",
          "placement": "bottom",
          "showLegend": true
        },
        "tooltip": {
          "mode": "single",
          "sort": "none"
        }
      },
      "targets": [
        {
          "datasource": {
            "type": "prometheus",
            "uid": "ci-logs-prod-aks-geneva-integration"
          },
          "editorMode": "code",
          "expr": "sum by (node) (rate(fluentbit_input_bytes_total{name=~\"$namespace-*\"}[5m]))",
          "legendFormat": "{{node}}",
          "range": true,
          "refId": "A"
        }
      ],
      "title": "Fluent-bit input bytes/s by Node",
      "type": "timeseries"
    },
    {
      "datasource": {
        "type": "prometheus",
        "uid": "ci-logs-prod-aks-geneva-integration"
      },
      "fieldConfig": {
        "defaults": {
          "color": {
            "mode": "palette-classic"
          },
          "custom": {
            "axisCenteredZero": false,
            "axisColorMode": "text",
            "axisLabel": "",
            "axisPlacement": "auto",
            "barAlignment": 0,
            "drawStyle": "line",
            "fillOpacity": 0,
            "gradientMode": "none",
            "hideFrom": {
              "legend": false,
              "tooltip": false,
              "viz": false
            },
            "lineInterpolation": "linear",
            "lineWidth": 1,
            "pointSize": 5,
            "scaleDistribution": {
              "type": "linear"
            },
            "showPoints": "auto",
            "spanNulls": false,
            "stacking": {
              "group": "A",
              "mode": "none"
            },
            "thresholdsStyle": {
              "mode": "off"
            }
          },
          "mappings": [],
          "thresholds": {
            "mode": "absolute",
            "steps": [
              {
                "color": "green",
                "value": null
              },
              {
                "color": "red",
                "value": 80
              }
            ]
          }
        },
        "overrides": []
      },
      "gridPos": {
        "h": 8,
        "w": 8,
        "x": 8,
        "y": 16
      },
      "id": 12,
      "options": {
        "legend": {
          "calcs": [],
          "displayMode": "list",
          "placement": "bottom",
          "showLegend": true
        },
        "tooltip": {
          "mode": "single",
          "sort": "none"
        }
      },
      "targets": [
        {
          "datasource": {
            "type": "prometheus",
            "uid": "ci-logs-prod-aks-geneva-integration"
          },
          "editorMode": "code",
          "expr": "sum by (node) (rate(fluentbit_output_proc_bytes_total{name=~\"$namespace-*\"}[5m]))",
          "legendFormat": "{{node}}",
          "range": true,
          "refId": "A"
        }
      ],
      "title": "Fluent-bit output process bytes/s by Node",
      "type": "timeseries"
    },
    {
      "datasource": {
        "type": "prometheus",
        "uid": "ci-logs-prod-aks-geneva-integration"
      },
      "fieldConfig": {
        "defaults": {
          "color": {
            "mode": "palette-classic"
          },
          "custom": {
            "axisCenteredZero": false,
            "axisColorMode": "text",
            "axisLabel": "",
            "axisPlacement": "auto",
            "barAlignment": 0,
            "drawStyle": "line",
            "fillOpacity": 0,
            "gradientMode": "none",
            "hideFrom": {
              "legend": false,
              "tooltip": false,
              "viz": false
            },
            "lineInterpolation": "linear",
            "lineWidth": 1,
            "pointSize": 5,
            "scaleDistribution": {
              "type": "linear"
            },
            "showPoints": "auto",
            "spanNulls": false,
            "stacking": {
              "group": "A",
              "mode": "none"
            },
            "thresholdsStyle": {
              "mode": "off"
            }
          },
          "mappings": [],
          "thresholds": {
            "mode": "absolute",
            "steps": [
              {
                "color": "green",
                "value": null
              },
              {
                "color": "red",
                "value": 80
              }
            ]
          }
        },
        "overrides": []
      },
      "gridPos": {
        "h": 8,
        "w": 8,
        "x": 0,
        "y": 24
      },
      "id": 14,
      "options": {
        "legend": {
          "calcs": [],
          "displayMode": "list",
          "placement": "bottom",
          "showLegend": true
        },
        "tooltip": {
          "mode": "single",
          "sort": "none"
        }
      },
      "targets": [
        {
          "datasource": {
            "type": "prometheus",
            "uid": "ci-logs-prod-aks-geneva-integration"
          },
          "editorMode": "code",
          "expr": "sum by () (rate(fluentbit_input_bytes_total{name=~\"$namespace-*\"}[5m]))",
          "legendFormat": "All",
          "range": true,
          "refId": "A"
        }
      ],
      "title": "Fluent-bit input bytes/s by All Nodes",
      "type": "timeseries"
    },
    {
      "datasource": {
        "type": "prometheus",
        "uid": "ci-logs-prod-aks-geneva-integration"
      },
      "fieldConfig": {
        "defaults": {
          "color": {
            "mode": "palette-classic"
          },
          "custom": {
            "axisCenteredZero": false,
            "axisColorMode": "text",
            "axisLabel": "",
            "axisPlacement": "auto",
            "barAlignment": 0,
            "drawStyle": "line",
            "fillOpacity": 0,
            "gradientMode": "none",
            "hideFrom": {
              "legend": false,
              "tooltip": false,
              "viz": false
            },
            "lineInterpolation": "linear",
            "lineWidth": 1,
            "pointSize": 5,
            "scaleDistribution": {
              "type": "linear"
            },
            "showPoints": "auto",
            "spanNulls": false,
            "stacking": {
              "group": "A",
              "mode": "none"
            },
            "thresholdsStyle": {
              "mode": "off"
            }
          },
          "mappings": [],
          "thresholds": {
            "mode": "absolute",
            "steps": [
              {
                "color": "green",
                "value": null
              },
              {
                "color": "red",
                "value": 80
              }
            ]
          }
        },
        "overrides": []
      },
      "gridPos": {
        "h": 8,
        "w": 8,
        "x": 8,
        "y": 24
      },
      "id": 16,
      "options": {
        "legend": {
          "calcs": [],
          "displayMode": "list",
          "placement": "bottom",
          "showLegend": true
        },
        "tooltip": {
          "mode": "single",
          "sort": "none"
        }
      },
      "targets": [
        {
          "datasource": {
            "type": "prometheus",
            "uid": "ci-logs-prod-aks-geneva-integration"
          },
          "editorMode": "code",
          "expr": "sum by () (rate(fluentbit_output_proc_bytes_total{name=~\"$namespace-*\"}[5m]))",
          "legendFormat": "All",
          "range": true,
          "refId": "A"
        }
      ],
      "title": "Fluent-bit output process bytes/s by All Nodes",
      "type": "timeseries"
    },
    {
      "datasource": {
        "type": "prometheus",
        "uid": "ci-logs-prod-aks-geneva-integration"
      },
      "fieldConfig": {
        "defaults": {
          "color": {
            "mode": "palette-classic"
          },
          "custom": {
            "axisCenteredZero": false,
            "axisColorMode": "text",
            "axisLabel": "",
            "axisPlacement": "auto",
            "barAlignment": 0,
            "drawStyle": "line",
            "fillOpacity": 0,
            "gradientMode": "none",
            "hideFrom": {
              "legend": false,
              "tooltip": false,
              "viz": false
            },
            "lineInterpolation": "linear",
            "lineWidth": 1,
            "pointSize": 5,
            "scaleDistribution": {
              "type": "linear"
            },
            "showPoints": "auto",
            "spanNulls": false,
            "stacking": {
              "group": "A",
              "mode": "none"
            },
            "thresholdsStyle": {
              "mode": "off"
            }
          },
          "mappings": [],
          "thresholds": {
            "mode": "absolute",
            "steps": [
              {
                "color": "green",
                "value": null
              },
              {
                "color": "red",
                "value": 80
              }
            ]
          }
        },
        "overrides": []
      },
      "gridPos": {
        "h": 4,
        "w": 8,
        "x": 0,
        "y": 32
      },
      "id": 20,
      "options": {
        "legend": {
          "calcs": [],
          "displayMode": "list",
          "placement": "bottom",
          "showLegend": true
        },
        "tooltip": {
          "mode": "single",
          "sort": "none"
        }
      },
      "targets": [
        {
          "datasource": {
            "type": "prometheus",
            "uid": "ci-logs-prod-aks-geneva-integration"
          },
          "editorMode": "code",
          "expr": "\r\nsum by (node) (rate(fluentbit_output_retries_failed_total{name=~\"$namespace_*\"}[5m]))",
          "legendFormat": "{{node}}",
          "range": true,
          "refId": "A"
        }
      ],
      "title": "Fluent-bit retries/fails",
      "type": "timeseries"
    },
    {
      "datasource": {
        "type": "prometheus",
        "uid": "ci-logs-prod-aks-geneva-integration"
      },
      "fieldConfig": {
        "defaults": {
          "color": {
            "mode": "palette-classic"
          },
          "custom": {
            "axisCenteredZero": false,
            "axisColorMode": "text",
            "axisLabel": "",
            "axisPlacement": "auto",
            "barAlignment": 0,
            "drawStyle": "line",
            "fillOpacity": 0,
            "gradientMode": "none",
            "hideFrom": {
              "legend": false,
              "tooltip": false,
              "viz": false
            },
            "lineInterpolation": "linear",
            "lineWidth": 1,
            "pointSize": 5,
            "scaleDistribution": {
              "type": "linear"
            },
            "showPoints": "auto",
            "spanNulls": false,
            "stacking": {
              "group": "A",
              "mode": "none"
            },
            "thresholdsStyle": {
              "mode": "off"
            }
          },
          "mappings": [],
          "thresholds": {
            "mode": "absolute",
            "steps": [
              {
                "color": "green",
                "value": null
              },
              {
                "color": "red",
                "value": 80
              }
            ]
          }
        },
        "overrides": []
      },
      "gridPos": {
        "h": 4,
        "w": 8,
        "x": 8,
        "y": 32
      },
      "id": 18,
      "options": {
        "legend": {
          "calcs": [],
          "displayMode": "list",
          "placement": "bottom",
          "showLegend": true
        },
        "tooltip": {
          "mode": "single",
          "sort": "none"
        }
      },
      "targets": [
        {
          "datasource": {
            "type": "prometheus",
            "uid": "ci-logs-prod-aks-geneva-integration"
          },
          "editorMode": "code",
          "expr": "sum by (node) (rate(fluentbit_output_dropped_records_total{name=~\"$namespace_*\"}[5m]))",
          "legendFormat": "{{node}}",
          "range": true,
          "refId": "A"
        }
      ],
      "title": "Fluent-bit output dropped records/s",
      "type": "timeseries"
    },
    {
      "datasource": {
        "type": "prometheus",
        "uid": "ci-logs-prod-aks-geneva-integration"
      },
      "fieldConfig": {
        "defaults": {
          "color": {
            "mode": "palette-classic"
          },
          "custom": {
            "axisCenteredZero": false,
            "axisColorMode": "text",
            "axisLabel": "",
            "axisPlacement": "auto",
            "barAlignment": 0,
            "drawStyle": "line",
            "fillOpacity": 0,
            "gradientMode": "none",
            "hideFrom": {
              "legend": false,
              "tooltip": false,
              "viz": false
            },
            "lineInterpolation": "linear",
            "lineWidth": 1,
            "pointSize": 5,
            "scaleDistribution": {
              "type": "linear"
            },
            "showPoints": "auto",
            "spanNulls": false,
            "stacking": {
              "group": "A",
              "mode": "none"
            },
            "thresholdsStyle": {
              "mode": "off"
            }
          },
          "mappings": [],
          "thresholds": {
            "mode": "absolute",
            "steps": [
              {
                "color": "green",
                "value": null
              },
              {
                "color": "red",
                "value": 80
              }
            ]
          }
        },
        "overrides": []
      },
      "gridPos": {
        "h": 8,
        "w": 16,
        "x": 0,
        "y": 36
      },
      "id": 22,
      "options": {
        "legend": {
          "calcs": [],
          "displayMode": "list",
          "placement": "bottom",
          "showLegend": true
        },
        "tooltip": {
          "mode": "single",
          "sort": "none"
        }
      },
      "targets": [
        {
          "datasource": {
            "type": "prometheus",
            "uid": "ci-logs-prod-aks-geneva-integration"
          },
          "editorMode": "code",
          "expr": "sum by (node) (rate(fluentbit_output_errors_total{name=~\"$namespace_*\"}[5m]))",
          "legendFormat": "{{node}}",
          "range": true,
          "refId": "A"
        }
      ],
      "title": "Fluent-bit output errors/sec",
      "type": "timeseries"
    }
  ],
  "refresh": "",
  "revision": 1,
  "schemaVersion": 38,
  "style": "dark",
  "tags": [],
  "templating": {
    "list": [
      {
        "current": {
          "selected": false,
          "text": "Managed_Prometheus_ci-logs-prod-aks-geneva-integration",
          "value": "Managed_Prometheus_ci-logs-prod-aks-geneva-integration"
        },
        "hide": 0,
        "includeAll": false,
        "multi": false,
        "name": "datasource",
        "options": [],
        "query": "prometheus",
        "refresh": 1,
        "regex": "",
        "skipUrlSync": false,
        "type": "datasource"
      },
      {
        "current": {
          "selected": false,
          "text": "ci-logs-prod-aks-geneva-integration-multi-tenancy",
          "value": "ci-logs-prod-aks-geneva-integration-multi-tenancy"
        },
        "datasource": {
          "type": "prometheus",
          "uid": "${datasource}"
        },
        "definition": "label_values(up{job=\"cadvisor\"}, cluster)",
        "hide": 0,
        "includeAll": false,
        "multi": false,
        "name": "cluster",
        "options": [],
        "query": {
          "query": "label_values(up{job=\"cadvisor\"}, cluster)",
          "refId": "StandardVariableQuery"
        },
        "refresh": 1,
        "regex": "",
        "skipUrlSync": false,
        "sort": 0,
        "type": "query"
      },
      {
        "current": {
          "selected": false,
          "text": "partner-1",
          "value": "partner-1"
        },
        "datasource": {
          "type": "prometheus",
          "uid": "${datasource}"
        },
        "definition": "label_values(kube_namespace_status_phase{job=\"kube-state-metrics\", cluster=\"$cluster\"}, namespace)",
        "description": "namespace",
        "hide": 0,
        "includeAll": false,
        "multi": false,
        "name": "namespace",
        "options": [],
        "query": {
          "query": "label_values(kube_namespace_status_phase{job=\"kube-state-metrics\", cluster=\"$cluster\"}, namespace)",
          "refId": "StandardVariableQuery"
        },
        "refresh": 1,
        "regex": "",
        "skipUrlSync": false,
        "sort": 0,
        "type": "query"
      }
    ]
  },
  "time": {
    "from": "now-15m",
    "to": "now"
  },
  "timepicker": {},
  "timezone": "",
  "title": "Azure Monitor for Containers - Geneva Logs Multitenacy- Platform",
  "uid": "E_FvdCC4z",
  "version": 12,
  "weekStart": ""
}
